CHANGES.txt
LICENSE.txt
MANIFEST.in
README.txt
setup.py
Products/__init__.py
Products.AutocompleteWidget.egg-info/PKG-INFO
Products.AutocompleteWidget.egg-info/SOURCES.txt
Products.AutocompleteWidget.egg-info/dependency_links.txt
Products.AutocompleteWidget.egg-info/namespace_packages.txt
Products.AutocompleteWidget.egg-info/not-zip-safe
Products.AutocompleteWidget.egg-info/requires.txt
Products.AutocompleteWidget.egg-info/top_level.txt
Products/AutocompleteWidget/AutocompleteWidget.py
Products/AutocompleteWidget/__init__.py
Products/AutocompleteWidget/config.py
Products/AutocompleteWidget/configure.zcml
Products/AutocompleteWidget/todo.txt
Products/AutocompleteWidget/version.txt
Products/AutocompleteWidget/locales/autocompletewidget.pot
Products/AutocompleteWidget/locales/de/LC_MESSAGES/autocompletewidget.mo
Products/AutocompleteWidget/locales/de/LC_MESSAGES/autocompletewidget.po
Products/AutocompleteWidget/locales/es/LC_MESSAGES/autocompletewidget.mo
Products/AutocompleteWidget/locales/es/LC_MESSAGES/autocompletewidget.po
Products/AutocompleteWidget/locales/fr/LC_MESSAGES/autocompletewidget.mo
Products/AutocompleteWidget/locales/fr/LC_MESSAGES/autocompletewidget.po
Products/AutocompleteWidget/profiles/default/metadata.xml
Products/AutocompleteWidget/profiles/default/propertiestool.xml
Products/AutocompleteWidget/profiles/default/skins.xml
Products/AutocompleteWidget/skins/actb_widget/actb_widget.css.dtml
Products/AutocompleteWidget/skins/actb_widget/actb_widget.js.dtml
Products/AutocompleteWidget/skins/actb_widget/atcb_separators.py
Products/AutocompleteWidget/skins/actb_widget/autocomplete.pt
Products/AutocompleteWidget/skins/actb_widget/delete_small_icon.gif