Metadata-Version: 1.1
Name: Products.AutocompleteWidget
Version: 1.5.0
Summary: Archetypes autocomplete widget with support for String-, Lines- and ReferenceFields
Home-page: http://plone.org/products/autocompletewidget/
Author: Jonathan Riboux, Alec Mitchell and contributors
Author-email: jonathan.riboux@quadra-informatique.fr, plone-developers@lists.sourceforge.net
License: see LICENSE.txt
Keywords: Zope Plone Archetypes
Platform: UNKNOWN
Classifier: Framework :: Zope2
Classifier: License :: OSI Approved :: Zope Public License
Classifier: Environment :: Web Environment
Classifier: Framework :: Plone
Classifier: Framework :: Plone :: 4.2
Classifier: Framework :: Plone :: 4.3
Classifier: Operating System :: OS Independent
Classifier: Programming Language :: Python
Classifier: Programming Language :: Python :: 2
Classifier: Programming Language :: Python :: 2.7
Classifier: Topic :: Software Development :: Libraries :: Python Modules
